keras_metrics/__init__.py
keras_metrics/casts.py
keras_metrics/metrics.py
keras_metrics-1.1.0.dist-info/LICENSE.txt
keras_metrics-1.1.0.dist-info/METADATA
keras_metrics-1.1.0.dist-info/WHEEL
keras_metrics-1.1.0.dist-info/top_level.txt
keras_metrics-1.1.0.dist-info/RECORD
