Metadata-Version: 2.1
Name: keras-metrics
Version: 1.1.0
Summary: Metrics for Keras model evaluation
Home-page: https://github.com/netrack/keras-metrics
Author: Yasha Bubnov
Author-email: girokompass@gmail.com
License: UNKNOWN
Keywords: keras metrics evaluation
Platform: UNKNOWN
Classifier: Intended Audience :: Developers
Classifier: License :: OSI Approved :: MIT License
Classifier: Topic :: Software Development :: Libraries
Classifier: Programming Language :: Python :: 2
Classifier: Programming Language :: Python :: 2.7
Classifier: Programming Language :: Python :: 3
Classifier: Programming Language :: Python :: 3.4
Classifier: Programming Language :: Python :: 3.5
Classifier: Programming Language :: Python :: 3.6
Requires-Dist: Keras (>=2.1.5)
